[
  {"name" : "AA50/1440",
   "codename" : "aa_50_1440",
   "location" : "outdoor",
   "body" : "AA",
   "family" : "aa1440",
   "passes" : [{"n_arrows" : 36, "diameter" : 122, "scoring" : "10_zone", "distance" : 50, "dist_unit" : "metre"},
               {"n_arrows" : 36, "diameter" : 122, "scoring" : "10_zone", "distance" : 40, "dist_unit" : "metre"},
               {"n_arrows" : 36, "diameter" : 80, "scoring" : "10_zone", "distance" : 30, "dist_unit" : "metre"},
               {"n_arrows" : 36, "diameter" : 80, "scoring" : "10_zone", "distance" : 20, "dist_unit" : "metre"}
              ]
  },
  {"name" : "AA40/1440",
   "codename" : "aa_40_1440",
   "location" : "outdoor",
   "body" : "AA",
   "family" : "aa1440",
   "passes" : [{"n_arrows" : 36, "diameter" : 122, "scoring" : "10_zone", "distance" : 40, "dist_unit" : "metre"},
               {"n_arrows" : 36, "diameter" : 122, "scoring" : "10_zone", "distance" : 30, "dist_unit" : "metre"},
               {"n_arrows" : 36, "diameter" : 80, "scoring" : "10_zone", "distance" : 30, "dist_unit" : "metre"},
               {"n_arrows" : 36, "diameter" : 80, "scoring" : "10_zone", "distance" : 20, "dist_unit" : "metre"}
              ]
  },


  {"name" : "Long Sydney",
   "codename" : "long_sydney",
   "location" : "outdoor",
   "body" : "AA",
   "family" : "sydney",
   "passes" : [{"n_arrows" : 30, "diameter" : 122, "scoring" : "10_zone", "distance" : 90, "dist_unit" : "metre"},
               {"n_arrows" : 30, "diameter" : 122, "scoring" : "10_zone", "distance" : 70, "dist_unit" : "metre"},
               {"n_arrows" : 30, "diameter" : 122, "scoring" : "10_zone", "distance" : 60, "dist_unit" : "metre"},
               {"n_arrows" : 30, "diameter" : 122, "scoring" : "10_zone", "distance" : 50, "dist_unit" : "metre"}
              ]
  },
  {"name" : "Sydney",
   "codename" : "sydney",
   "location" : "outdoor",
   "body" : "AA",
   "family" : "sydney",
   "passes" : [{"n_arrows" : 30, "diameter" : 122, "scoring" : "10_zone", "distance" : 70, "dist_unit" : "metre"},
               {"n_arrows" : 30, "diameter" : 122, "scoring" : "10_zone", "distance" : 60, "dist_unit" : "metre"},
               {"n_arrows" : 30, "diameter" : 122, "scoring" : "10_zone", "distance" : 50, "dist_unit" : "metre"},
               {"n_arrows" : 30, "diameter" : 122, "scoring" : "10_zone", "distance" : 40, "dist_unit" : "metre"}
              ]
  },


  {"name" : "Long Brisbane",
   "codename" : "long_brisbane",
   "location" : "outdoor",
   "body" : "AA",
   "family" : "brisbane",
   "passes" : [{"n_arrows" : 30, "diameter" : 122, "scoring" : "10_zone", "distance" : 90, "dist_unit" : "metre"},
               {"n_arrows" : 30, "diameter" : 122, "scoring" : "10_zone", "distance" : 70, "dist_unit" : "metre"},
               {"n_arrows" : 30, "diameter" : 80, "scoring" : "10_zone", "distance" : 60, "dist_unit" : "metre"},
               {"n_arrows" : 30, "diameter" : 80, "scoring" : "10_zone", "distance" : 50, "dist_unit" : "metre"}
              ]
  },
  {"name" : "Brisbane",
   "codename" : "brisbane",
   "location" : "outdoor",
   "body" : "AA",
   "family" : "brisbane",
   "passes" : [{"n_arrows" : 30, "diameter" : 122, "scoring" : "10_zone", "distance" : 70, "dist_unit" : "metre"},
               {"n_arrows" : 30, "diameter" : 122, "scoring" : "10_zone", "distance" : 60, "dist_unit" : "metre"},
               {"n_arrows" : 30, "diameter" : 80, "scoring" : "10_zone", "distance" : 50, "dist_unit" : "metre"},
               {"n_arrows" : 30, "diameter" : 80, "scoring" : "10_zone", "distance" : 40, "dist_unit" : "metre"}
              ]
  },
  {"name" : "Adelaide",
   "codename" : "adelaide",
   "location" : "outdoor",
   "body" : "AA",
   "family" : "adelaide",
   "passes" : [{"n_arrows" : 30, "diameter" : 122, "scoring" : "10_zone", "distance" : 60, "dist_unit" : "metre"},
               {"n_arrows" : 30, "diameter" : 122, "scoring" : "10_zone", "distance" : 50, "dist_unit" : "metre"},
               {"n_arrows" : 30, "diameter" : 80, "scoring" : "10_zone", "distance" : 40, "dist_unit" : "metre"},
               {"n_arrows" : 30, "diameter" : 80, "scoring" : "10_zone", "distance" : 30, "dist_unit" : "metre"}
              ]
  },
  {"name" : "Short Adelaide",
   "codename" : "short_adelaide",
   "location" : "outdoor",
   "body" : "AA",
   "family" : "adelaide",
   "passes" : [{"n_arrows" : 30, "diameter" : 122, "scoring" : "10_zone", "distance" : 50, "dist_unit" : "metre"},
               {"n_arrows" : 30, "diameter" : 122, "scoring" : "10_zone", "distance" : 40, "dist_unit" : "metre"},
               {"n_arrows" : 30, "diameter" : 80, "scoring" : "10_zone", "distance" : 30, "dist_unit" : "metre"},
               {"n_arrows" : 30, "diameter" : 80, "scoring" : "10_zone", "distance" : 20, "dist_unit" : "metre"}
              ]
  },


  {"name" : "Hobart",
   "codename" : "hobart",
   "location" : "outdoor",
   "body" : "AA",
   "family" : "aa900",
   "passes" : [{"n_arrows" : 30, "diameter" : 122, "scoring" : "10_zone", "distance" : 90, "dist_unit" : "metre"},
               {"n_arrows" : 30, "diameter" : 122, "scoring" : "10_zone", "distance" : 70, "dist_unit" : "metre"},
               {"n_arrows" : 30, "diameter" : 122, "scoring" : "10_zone", "distance" : 50, "dist_unit" : "metre"}
              ]
  },
  {"name" : "Perth",
   "codename" : "perth",
   "location" : "outdoor",
   "body" : "AA",
   "family" : "aa900",
   "passes" : [{"n_arrows" : 30, "diameter" : 122, "scoring" : "10_zone", "distance" : 70, "dist_unit" : "metre"},
               {"n_arrows" : 30, "diameter" : 122, "scoring" : "10_zone", "distance" : 60, "dist_unit" : "metre"},
               {"n_arrows" : 30, "diameter" : 122, "scoring" : "10_zone", "distance" : 50, "dist_unit" : "metre"}
              ]
  },
  {"name" : "Canberra",
   "codename" : "canberra",
   "location" : "outdoor",
   "body" : "AA",
   "family" : "aa900",
   "passes" : [{"n_arrows" : 30, "diameter" : 122, "scoring" : "10_zone", "distance" : 60, "dist_unit" : "metre"},
               {"n_arrows" : 30, "diameter" : 122, "scoring" : "10_zone", "distance" : 50, "dist_unit" : "metre"},
               {"n_arrows" : 30, "diameter" : 122, "scoring" : "10_zone", "distance" : 40, "dist_unit" : "metre"}
              ]
  },
  {"name" : "Short Canberra",
   "codename" : "short_canberra",
   "location" : "outdoor",
   "body" : "AA",
   "family" : "aa900",
   "passes" : [{"n_arrows" : 30, "diameter" : 122, "scoring" : "10_zone", "distance" : 50, "dist_unit" : "metre"},
               {"n_arrows" : 30, "diameter" : 122, "scoring" : "10_zone", "distance" : 40, "dist_unit" : "metre"},
               {"n_arrows" : 30, "diameter" : 122, "scoring" : "10_zone", "distance" : 30, "dist_unit" : "metre"}
              ]
  },
  {"name" : "Junior Canberra",
   "codename" : "junior_canberra",
   "location" : "outdoor",
   "body" : "AA",
   "family" : "aa900",
   "passes" : [{"n_arrows" : 30, "diameter" : 122, "scoring" : "10_zone", "distance" : 40, "dist_unit" : "metre"},
               {"n_arrows" : 30, "diameter" : 122, "scoring" : "10_zone", "distance" : 30, "dist_unit" : "metre"},
               {"n_arrows" : 30, "diameter" : 122, "scoring" : "10_zone", "distance" : 20, "dist_unit" : "metre"}
              ]
  },
  {"name" : "Mini Canberra",
   "codename" : "mini_canberra",
   "location" : "outdoor",
   "body" : "AA",
   "family" : "aa900",
   "passes" : [{"n_arrows" : 30, "diameter" : 122, "scoring" : "10_zone", "distance" : 30, "dist_unit" : "metre"},
               {"n_arrows" : 30, "diameter" : 122, "scoring" : "10_zone", "distance" : 20, "dist_unit" : "metre"},
               {"n_arrows" : 30, "diameter" : 122, "scoring" : "10_zone", "distance" : 10, "dist_unit" : "metre"}
              ]
  },


  {"name" : "Grange",
   "codename" : "grange",
   "location" : "outdoor",
   "body" : "AA",
   "family" : "aa900_single_distance",
   "passes" : [{"n_arrows" : 30, "diameter" : 122, "scoring" : "10_zone", "distance" : 60, "dist_unit" : "metre"},
               {"n_arrows" : 30, "diameter" : 122, "scoring" : "10_zone", "distance" : 60, "dist_unit" : "metre"},
               {"n_arrows" : 30, "diameter" : 122, "scoring" : "10_zone", "distance" : 60, "dist_unit" : "metre"}
              ]
  },
  {"name" : "Melbourne",
   "codename" : "melbourne",
   "location" : "outdoor",
   "body" : "AA",
   "family" : "aa900_single_distance",
   "passes" : [{"n_arrows" : 30, "diameter" : 122, "scoring" : "10_zone", "distance" : 50, "dist_unit" : "metre"},
               {"n_arrows" : 30, "diameter" : 122, "scoring" : "10_zone", "distance" : 50, "dist_unit" : "metre"},
               {"n_arrows" : 30, "diameter" : 122, "scoring" : "10_zone", "distance" : 50, "dist_unit" : "metre"}
              ]
  },
  {"name" : "Darwin",
   "codename" : "darwin",
   "location" : "outdoor",
   "body" : "AA",
   "family" : "aa900_single_distance",
   "passes" : [{"n_arrows" : 30, "diameter" : 122, "scoring" : "10_zone", "distance" : 40, "dist_unit" : "metre"},
               {"n_arrows" : 30, "diameter" : 122, "scoring" : "10_zone", "distance" : 40, "dist_unit" : "metre"},
               {"n_arrows" : 30, "diameter" : 122, "scoring" : "10_zone", "distance" : 40, "dist_unit" : "metre"}
              ]
  },
  {"name" : "Geelong",
   "codename" : "geelong",
   "location" : "outdoor",
   "body" : "AA",
   "family" : "aa900_single_distance",
   "passes" : [{"n_arrows" : 30, "diameter" : 122, "scoring" : "10_zone", "distance" : 30, "dist_unit" : "metre"},
               {"n_arrows" : 30, "diameter" : 122, "scoring" : "10_zone", "distance" : 30, "dist_unit" : "metre"},
               {"n_arrows" : 30, "diameter" : 122, "scoring" : "10_zone", "distance" : 30, "dist_unit" : "metre"}
              ]
  },
  {"name" : "Newcastle",
   "codename" : "newcastle",
   "location" : "outdoor",
   "body" : "AA",
   "family" : "aa900_single_distance",
   "passes" : [{"n_arrows" : 30, "diameter" : 122, "scoring" : "10_zone", "distance" : 20, "dist_unit" : "metre"},
               {"n_arrows" : 30, "diameter" : 122, "scoring" : "10_zone", "distance" : 20, "dist_unit" : "metre"},
               {"n_arrows" : 30, "diameter" : 122, "scoring" : "10_zone", "distance" : 20, "dist_unit" : "metre"}
              ]
  },
  {"name" : "Holt",
   "codename" : "holt",
   "location" : "outdoor",
   "body" : "AA",
   "family" : "aa900_single_distance",
   "passes" : [{"n_arrows" : 30, "diameter" : 80, "scoring" : "10_zone", "distance" : 50, "dist_unit" : "metre"},
               {"n_arrows" : 30, "diameter" : 80, "scoring" : "10_zone", "distance" : 50, "dist_unit" : "metre"},
               {"n_arrows" : 30, "diameter" : 80, "scoring" : "10_zone", "distance" : 50, "dist_unit" : "metre"}
              ]
  },
  {"name" : "Samford",
   "codename" : "samford",
   "location" : "outdoor",
   "body" : "AA",
   "family" : "aa900_single_distance",
   "passes" : [{"n_arrows" : 30, "diameter" : 80, "scoring" : "10_zone", "distance" : 40, "dist_unit" : "metre"},
               {"n_arrows" : 30, "diameter" : 80, "scoring" : "10_zone", "distance" : 40, "dist_unit" : "metre"},
               {"n_arrows" : 30, "diameter" : 80, "scoring" : "10_zone", "distance" : 40, "dist_unit" : "metre"}
              ]
  },
  {"name" : "Drake",
   "codename" : "drake",
   "location" : "outdoor",
   "body" : "AA",
   "family" : "aa900_single_distance",
   "passes" : [{"n_arrows" : 30, "diameter" : 80, "scoring" : "10_zone", "distance" : 30, "dist_unit" : "metre"},
               {"n_arrows" : 30, "diameter" : 80, "scoring" : "10_zone", "distance" : 30, "dist_unit" : "metre"},
               {"n_arrows" : 30, "diameter" : 80, "scoring" : "10_zone", "distance" : 30, "dist_unit" : "metre"}
              ]
  },


  {"name" : "Wollongong",
   "codename" : "wollongong",
   "location" : "outdoor",
   "body" : "AA",
   "family" : "aa720_split_distance",
   "passes" : [{"n_arrows" : 36, "diameter" : 122, "scoring" : "10_zone", "distance" : 90, "dist_unit" : "metre"},
               {"n_arrows" : 36, "diameter" : 122, "scoring" : "10_zone", "distance" : 70, "dist_unit" : "metre"}
              ]
  },
  {"name" : "Townsville",
   "codename" : "townsville",
   "location" : "outdoor",
   "body" : "AA",
   "family" : "aa720_split_distance",
   "passes" : [{"n_arrows" : 36, "diameter" : 122, "scoring" : "10_zone", "distance" : 70, "dist_unit" : "metre"},
               {"n_arrows" : 36, "diameter" : 122, "scoring" : "10_zone", "distance" : 60, "dist_unit" : "metre"}
              ]
  },
  {"name" : "Launceston",
   "codename" : "launceston",
   "location" : "outdoor",
   "body" : "AA",
   "family" : "aa720_split_distance",
   "passes" : [{"n_arrows" : 36, "diameter" : 80, "scoring" : "10_zone", "distance" : 50, "dist_unit" : "metre"},
               {"n_arrows" : 36, "diameter" : 80, "scoring" : "10_zone", "distance" : 30, "dist_unit" : "metre"}
              ]
  },


  {"name" : "AA50/720",
   "codename" : "aa_50_720",
   "location" : "outdoor",
   "body" : "AA",
   "family" : "aa720",
   "passes" : [{"n_arrows" : 36, "diameter" : 122, "scoring" : "10_zone", "distance" : 50, "dist_unit" : "metre"},
               {"n_arrows" : 36, "diameter" : 122, "scoring" : "10_zone", "distance" : 50, "dist_unit" : "metre"}
              ]
  },
  {"name" : "AA40/720",
   "codename" : "aa_40_720",
   "location" : "outdoor",
   "body" : "AA",
   "family" : "aa720",
   "passes" : [{"n_arrows" : 36, "diameter" : 122, "scoring" : "10_zone", "distance" : 40, "dist_unit" : "metre"},
               {"n_arrows" : 36, "diameter" : 122, "scoring" : "10_zone", "distance" : 40, "dist_unit" : "metre"}
              ]
  },
  {"name" : "AA30/720",
   "codename" : "aa_30_720",
   "location" : "outdoor",
   "body" : "AA",
   "family" : "aa720",
   "passes" : [{"n_arrows" : 36, "diameter" : 122, "scoring" : "10_zone", "distance" : 30, "dist_unit" : "metre"},
               {"n_arrows" : 36, "diameter" : 122, "scoring" : "10_zone", "distance" : 30, "dist_unit" : "metre"}
              ]
  },
  {"name" : "AA20/720",
   "codename" : "aa_20_720",
   "location" : "outdoor",
   "body" : "AA",
   "family" : "aa720",
   "passes" : [{"n_arrows" : 36, "diameter" : 122, "scoring" : "10_zone", "distance" : 30, "dist_unit" : "metre"},
               {"n_arrows" : 36, "diameter" : 122, "scoring" : "10_zone", "distance" : 30, "dist_unit" : "metre"}
              ]
  }
]
